Workbook

Sheet Dados
A1: Coluna 1 | B1: Descrição | C1: Movimento | D1: Valor
A2: 45658 | B2: Fatura Eletricidade | C2: Débito | D2: 65.56
A3: 45660 | B3: Supermercado Délice | C3: Débito | D3: 42.75 | F3: Recebimento | G3: =SUMIF(Dados!C2:C1000,"=*crédito*",Dados!D2:D1000) -> 2590.49
A4: 45661 | B4: Transferência Recibida - João | C4: Crédito | D4: 250 | F4: Gastos | G4: =SUMIF(Dados!C2:C1000,"=*débito*",Dados!D2:D1000) -> 990.7
A5: 45662 | B5: Cafeteria Central | C5: Débito | D5: 3.2 | F5: TOTAL | G5: =G3-G4 -> 1599.79
A6: 45664 | B6: Pagamento de Renda | C6: Débito | D6: 650
A7: 45666 | B7: Reembolso Plataforma X | C7: Crédito | D7: 15.5
A8: 45667 | B8: Restaurante Solar | C8: Débito | D8: 27.4
A9: 45700 | B9: Salário Mensal | C9: Crédito | D9: 1850
A10: 45701 | B10: Compra Online - Livraria | C10: Débito | D10: 18.9
A11: 45702 | B11: Subscrição Streaming | C11: Débito | D11: 7.99
A12: 45703 | B12: Transferência Recebida - Maria | C12: Crédito | D12: 120
A13: 45704 | B13: Gasolina - Posto Norte | C13: Débito | D13: 55.8
A14: 45705 | B14: Farmácia Saúde | C14: Débito | D14: 12.6
A15: 45706 | B15: Devolução Compra Online | C15: Crédito | D15: 9.99
A16: 45707 | B16: Padaria Trigo Doce | C16: Débito | D16: 4.5
A17: 45738 | B17: Supermercado Délice | C17: Débito | D17: 38.1
... A22: 45743 | B22: Reembolso Seguro | C22: Crédito | D22: 45
D23: 0
D24: 0
D25: 0
D26: 0
D27: 0
D28: 0
D29: 0
D30: 0
D31: 0
D32: 0
D33: 0
D34: 0
... D57: 0

Sheet Dashboard
B3: Sumário
B4: Total de gastos
B5: =SUMIF(Dados!C2:C1000,"=*crédito*",Dados!D2:D1000) -> 2590.49
B7: Total de recebimento
B8: =SUMIF(Dados!C2:C1000,"=*débito*",Dados!D2:D1000) -> 990.7
B10: Total de saldo
B11: =Dados!G5 -> 1599.79
B14: Detalhe Mensal
B15: SELECIONE MÊS
B16: fevereiro
C35: =mesToNumero(B16) -> 2 | D35: =IFERROR(__xludf.DUMMYFUNCTION("FILTER(Dados!C2:D1000, MONTH(Dados!A2:A1000)=C35)"),"Crédito") -> Crédito | E35: =IFERROR(__xludf.DUMMYFUNCTION("""COMPUTED_VALUE"""),1850.0) -> 1850
D36: =IFERROR(__xludf.DUMMYFUNCTION("""COMPUTED_VALUE"""),"Débito") -> Débito | E36: =IFERROR(__xludf.DUMMYFUNCTION("""COMPUTED_VALUE"""),18.9) -> 18.9
D37: =IFERROR(__xludf.DUMMYFUNCTION("""COMPUTED_VALUE"""),"Débito") -> Débito | E37: =IFERROR(__xludf.DUMMYFUNCTION("""COMPUTED_VALUE"""),7.99) -> 7.99
D38: =IFERROR(__xludf.DUMMYFUNCTION("""COMPUTED_VALUE"""),"Crédito") -> Crédito | E38: =IFERROR(__xludf.DUMMYFUNCTION("""COMPUTED_VALUE"""),120.0) -> 120
D39: =IFERROR(__xludf.DUMMYFUNCTION("""COMPUTED_VALUE"""),"Débito") -> Débito | E39: =IFERROR(__xludf.DUMMYFUNCTION("""COMPUTED_VALUE"""),55.8) -> 55.8
D40: =IFERROR(__xludf.DUMMYFUNCTION("""COMPUTED_VALUE"""),"Débito") -> Débito | E40: =IFERROR(__xludf.DUMMYFUNCTION("""COMPUTED_VALUE"""),12.6) -> 12.6
D41: =IFERROR(__xludf.DUMMYFUNCTION("""COMPUTED_VALUE"""),"Crédito") -> Crédito | E41: =IFERROR(__xludf.DUMMYFUNCTION("""COMPUTED_VALUE"""),9.99) -> 9.99
D42: =IFERROR(__xludf.DUMMYFUNCTION("""COMPUTED_VALUE"""),"Débito") -> Débito | E42: =IFERROR(__xludf.DUMMYFUNCTION("""COMPUTED_VALUE"""),4.5) -> 4.5
